LICENSE
MANIFEST.in
README.rst
setup.py
mongolog/__init__.py
mongolog/handlers.py
mongolog.egg-info/PKG-INFO
mongolog.egg-info/SOURCES.txt
mongolog.egg-info/dependency_links.txt
mongolog.egg-info/requires.txt
mongolog.egg-info/top_level.txt