Metadata-Version: 1.2
Name: mongolog
Version: 0.1.2
Summary: Centralized logging made simple using MongoDB
Home-page: https://github.com/puentesarrin/mongodb-log
Author: Andrei Savu
Author-email: contact@andreisavu.ro
Maintainer: Jorge Puente Sarrín
Maintainer-email: puentesarrin@gmail.com
License: UNKNOWN
Keywords: mongolog,logging,mongo,mongodb
Platform: UNKNOWN
Classifier: Development Status :: 5 - Production/Stable
Classifier: Intended Audience :: Developers
Classifier: Operating System :: OS Independent
Classifier: Programming Language :: Python
Classifier: Topic :: System :: Logging
Classifier: Topic :: Database
Requires-Python: >=2.7,!=3.0.*,!=3.1.*,!=3.2.*,!=3.3.*
